fast_generic_api/__init__.py
fast_generic_api/decorator.py
fast_generic_api/generics.py
fast_generic_api/mixins.py
fast_generic_api/core/__init__.py
fast_generic_api/core/exceptions.py
fast_generic_api/core/filter.py
fast_generic_api/core/pagination.py
fast_generic_api/core/response.py
fast_generic_api/core/serializers.py
fast_generic_api/core/status.py
fast_generic_api-0.1.6.dist-info/licenses/LICENSE
fast_generic_api-0.1.6.dist-info/METADATA
fast_generic_api-0.1.6.dist-info/WHEEL
fast_generic_api-0.1.6.dist-info/top_level.txt
fast_generic_api-0.1.6.dist-info/RECORD
